LICENSE
MANIFEST.in
README.md
requirements.txt
setup.py
rebound_pymc3/__init__.py
rebound_pymc3/build_utils.py
rebound_pymc3/integrate.cc
rebound_pymc3/integrate.py
rebound_pymc3/integrate_test.py
rebound_pymc3/python_impl.py
rebound_pymc3/python_impl_test.py
rebound_pymc3/rebound_pymc3_version.py
rebound_pymc3/theano_helpers.h
rebound_pymc3.egg-info/PKG-INFO
rebound_pymc3.egg-info/SOURCES.txt
rebound_pymc3.egg-info/dependency_links.txt
rebound_pymc3.egg-info/not-zip-safe
rebound_pymc3.egg-info/requires.txt
rebound_pymc3.egg-info/top_level.txt