Metadata-Version: 2.1
Name: rebound-pymc3
Version: 0.0.2
Summary: Fast & scalable MCMC for all your exoplanet needs
Home-page: https://github.com/dfm/rebound_pymc3
Author: Daniel Foreman-Mackey
Author-email: foreman.mackey@gmail.com
License: MIT
Platform: UNKNOWN
Classifier: Development Status :: 4 - Beta
Classifier: Intended Audience :: Developers
Classifier: Intended Audience :: Science/Research
Classifier: License :: OSI Approved :: GNU General Public License v3 or later (GPLv3+)
Classifier: Operating System :: OS Independent
Classifier: Programming Language :: Python
